pt_supermarket_scraper.py
pt_supermarket_scraper-0.1.0.dist-info/LICENSE
pt_supermarket_scraper-0.1.0.dist-info/METADATA
pt_supermarket_scraper-0.1.0.dist-info/WHEEL
pt_supermarket_scraper-0.1.0.dist-info/entry_points.txt
pt_supermarket_scraper-0.1.0.dist-info/top_level.txt
pt_supermarket_scraper-0.1.0.dist-info/RECORD
